craft.py
craft_reconstruct-1.0.0.dist-info/LICENSE
craft_reconstruct-1.0.0.dist-info/METADATA
craft_reconstruct-1.0.0.dist-info/WHEEL
craft_reconstruct-1.0.0.dist-info/top_level.txt
craft_reconstruct-1.0.0.dist-info/RECORD
