Metadata-Version: 2.1
Name: craft-reconstruct
Version: 1.0.0
Summary: An Iterative Reconstruction Algorithm for Faraday Tomography.
Home-page: https://github.com/suchethac/craft
Author: Suchetha Cooray
Author-email: cooray@nagoya-u.jp
License: MIT
Platform: UNKNOWN
Classifier: License :: OSI Approved :: MIT License
Classifier: Programming Language :: Python
Classifier: Programming Language :: Python :: 3
Classifier: Programming Language :: Python :: 3.6
Classifier: Programming Language :: Python :: Implementation :: CPython
Requires-Python: >=3.6.0
License-File: LICENSE
Requires-Dist: numpy
Requires-Dist: scipy
Provides-Extra: fftw
Requires-Dist: pyfftw ; extra == 'fftw'
